noahs_keyboard_tracker/__init__.py
noahs_keyboard_tracker/tracker.py
noahs_keyboard_tracker-0.1.0.dist-info/METADATA
noahs_keyboard_tracker-0.1.0.dist-info/WHEEL
noahs_keyboard_tracker-0.1.0.dist-info/top_level.txt
noahs_keyboard_tracker-0.1.0.dist-info/RECORD
