Metadata-Version: 2.4
Name: noahs_keyboard_tracker
Version: 0.1.0
Summary: A simple tool for Mac, Windows and Linux for monitoring keyboard input
Author-email: Noah Jones <jonesnoah45010@gmail.com>
License: MIT
Project-URL: GitHub, https://github.com/jonesnoah45010/keyboard_tracker
Classifier: Programming Language :: Python :: 3
Classifier: Operating System :: OS Independent
Classifier: License :: OSI Approved :: MIT License
Classifier: Intended Audience :: Developers
Classifier: Environment :: Console
Classifier: Topic :: Software Development :: Libraries :: Python Modules
Requires-Python: >=3.9
Requires-Dist: pynput; platform_system == "Windows" or platform_system == "Darwin"
Requires-Dist: evdev; platform_system == "Linux"
